cmdinterface/CmdInterface.py
cmdinterface/__init__.py
simplecmdinterface-0.3.0.dist-info/LICENSE
simplecmdinterface-0.3.0.dist-info/METADATA
simplecmdinterface-0.3.0.dist-info/WHEEL
simplecmdinterface-0.3.0.dist-info/top_level.txt
simplecmdinterface-0.3.0.dist-info/RECORD
