Metadata-Version: 2.1
Name: simplecmdinterface
Version: 0.3.0
Summary: A simple windows command line interface wrapper for use with cli's
Home-page: https://github.com/Skorpinakos/Simple-CMD-Interface-for-Python
Author: Ioannis Tsampras
Author-email: ioannis.tsampras@ac.upatras.gr
Classifier: Programming Language :: Python :: 3
Classifier: License :: OSI Approved :: MIT License
Classifier: Operating System :: Microsoft :: Windows
Requires-Python: >=3.8
License-File: LICENSE
